{
    "credentials": {
        "batch": {
            "account": "",
            "account_key": "",
            "account_service_url": ""
        },
        "storage": {
            "mystorageaccount": {
                "account": "",
                "account_key": "",
                "endpoint": "core.windows.net"
            }
        },
        "docker_registry": {
            "hub": {
                "username": "publichubuser",
                "password": "mypassword"
            },
            "myserver-myorg.azurecr.io": {
                "username": "azurecruser",
                "password": "mypassword"
            }
        }
    }
}
